configirl/__init__.py
configirl/_version.py
configirl/__pycache__/__init__.cpython-38.pyc
configirl/docs/__init__.py
configirl/tests/__init__.py
configirl/tests/config.py
configirl/tests/__pycache__/__init__.cpython-38.pyc
configirl/tests/__pycache__/config.cpython-38.pyc
configirl-1.0.1.dist-info/AUTHORS.rst
configirl-1.0.1.dist-info/LICENSE.txt
configirl-1.0.1.dist-info/METADATA
configirl-1.0.1.dist-info/WHEEL
configirl-1.0.1.dist-info/entry_points.txt
configirl-1.0.1.dist-info/top_level.txt
configirl-1.0.1.dist-info/RECORD
