Metadata-Version: 2.1
Name: configirl
Version: 1.0.1
Summary: Centralized Config Management Tool.
Home-page: https://github.com/MacHu-GWU/configirl-project
Author: Sanhe Hu
Author-email: husanhe@gmail.com
Maintainer: Unknown
License: MIT
Download-URL: https://pypi.python.org/pypi/configirl/1.0.1#downloads
Platform: Windows
Platform: MacOS
Platform: Unix
Classifier: Development Status :: 5 - Production/Stable
Classifier: Intended Audience :: Developers
Classifier: License :: OSI Approved :: MIT License
Classifier: Natural Language :: English
Classifier: Operating System :: Microsoft :: Windows
Classifier: Operating System :: MacOS
Classifier: Operating System :: Unix
Classifier: Programming Language :: Python
Classifier: Programming Language :: Python :: 2.7
Classifier: Programming Language :: Python :: 3.6
Classifier: Programming Language :: Python :: 3.7
Classifier: Programming Language :: Python :: 3.8
Classifier: Programming Language :: Python :: 3.9
License-File: LICENSE.txt
License-File: AUTHORS.rst
Provides-Extra: docs
Requires-Dist: sphinx (==1.8.1) ; extra == 'docs'
Requires-Dist: sphinx-rtd-theme ; extra == 'docs'
Requires-Dist: sphinx-jinja ; extra == 'docs'
Requires-Dist: sphinx-copybutton ; extra == 'docs'
Requires-Dist: docfly (>=0.0.17) ; extra == 'docs'
Requires-Dist: rstobj (>=0.0.5) ; extra == 'docs'
Requires-Dist: pygments ; extra == 'docs'
Provides-Extra: tests
Requires-Dist: pytest (==3.2.3) ; extra == 'tests'
Requires-Dist: pytest-cov (==2.5.1) ; extra == 'tests'
